[
    {
        "id": 1,
        "word": "veux",
        "choices": [
            "يريد",
            "لديه",
            "قرر"
        ],
        "correctAnswer": "يريد"
    },
    {
        "id": 2,
        "word": "a",
        "choices": [
            "لديه",
            "يأتي",
            "عند"
        ],
        "correctAnswer": "لديه"
    },
    {
        "id": 3,
        "word": "ronde",
        "choices": [
            "دائرة",
            "مستديرة",
            "مستديرة"
        ],
        "correctAnswer": "دائرة"
    },
    {
        "id": 4,
        "word": "retourna",
        "choices": [
            "عاد",
            "استعرض",
            "عاد"
        ],
        "correctAnswer": "عاد"
    },
    {
        "id": 5,
        "word": "crocodile",
        "choices": [
            "تمساح",
            "ضفدع",
            "سمكة"
        ],
        "correctAnswer": "تمساح"
    },
    {
        "id": 6,
        "word": "résolut",
        "choices": [
            "حل",
            "قرر",
            "نجح"
        ],
        "correctAnswer": "حل"
    },
    {
        "id": 7,
        "word": "rive",
        "choices": [
            "ضفة",
            "شاطئ",
            "نهر"
        ],
        "correctAnswer": "ضفة"
    },
    {
        "id": 8,
        "word": "montrer",
        "choices": [
            "عرض",
            "أظهر",
            "أخفى"
        ],
        "correctAnswer": "أظهر"
    },
    {
        "id": 9,
        "word": "vivre",
        "choices": [
            "يعيش",
            "يرى",
            "يتنفس"
        ],
        "correctAnswer": "يعيش"
    },
    {
        "id": 10,
        "word": "surpris",
        "choices": [
            "مفاجأ",
            "سعيد",
            "حزين"
        ],
        "correctAnswer": "مفاجأ"
    },
    {
        "id": 11,
        "word": "dit",
        "choices": [
            "قال",
            "طلب",
            "رفض"
        ],
        "correctAnswer": "قال"
    },
    {
        "id": 12,
        "word": "grand",
        "choices": [
            "كبير",
            "صغير",
            "ضخم"
        ],
        "correctAnswer": "كبير"
    },
    {
        "id": 13,
        "word": "aussi",
        "choices": [
            "أيضًا",
            "فقط",
            "بالفعل"
        ],
        "correctAnswer": "أيضًا"
    },
    {
        "id": 14,
        "word": "celle",
        "choices": [
            "تلك",
            "هذه",
            "هؤلاء"
        ],
        "correctAnswer": "تلك"
    },
    {
        "id": 15,
        "word": "pondre",
        "choices": [
            "تسريح",
            "إنجاب",
            "صياغة"
        ],
        "correctAnswer": "تسريح"
    },
    {
        "id": 16,
        "word": "fleuve",
        "choices": [
            "نهر",
            "بحيرة",
            "محيط"
        ],
        "correctAnswer": "نهر"
    },
    {
        "id": 17,
        "word": "trouver",
        "choices": [
            "يجد",
            "يخسر",
            "يتساءل"
        ],
        "correctAnswer": "يجد"
    },
    {
        "id": 18,
        "word": "interroger",
        "choices": [
            "استجواب",
            "يسأل",
            "يحكم"
        ],
        "correctAnswer": "يسأل"
    },
    {
        "id": 19,
        "word": "chaque",
        "choices": [
            "كل",
            "بعض",
            "قليل"
        ],
        "correctAnswer": "كل"
    },
    {
        "id": 20,
        "word": "ramasser",
        "choices": [
            "يجمع",
            "يرمي",
            "يحطم"
        ],
        "correctAnswer": "يجمع"
    },
    {
        "id": 21,
        "word": "question",
        "choices": [
            "سؤال",
            "جواب",
            "رأي"
        ],
        "correctAnswer": "سؤال"
    },
    {
        "id": 22,
        "word": "grasse",
        "choices": [
            "دهنية",
            "رقيقة",
            "كثيفة"
        ],
        "correctAnswer": "دهنية"
    },
    {
        "id": 23,
        "word": "ainsi",
        "choices": [
            "هكذا",
            "هناك",
            "بذلك"
        ],
        "correctAnswer": "هكذا"
    },
    {
        "id": 24,
        "word": "donc",
        "choices": [
            "لذلك",
            "هكذا",
            "ثم"
        ],
        "correctAnswer": "لذلك"
    },
    {
        "id": 25,
        "word": "approche",
        "choices": [
            "اقترب",
            "ابتعد",
            "دفع"
        ],
        "correctAnswer": "اقترب"
    },
    {
        "id": 26,
        "word": "incertitude",
        "choices": [
            "عدم اليقين",
            "تأكيد",
            "قناعة"
        ],
        "correctAnswer": "عدم اليقين"
    },
    {
        "id": 27,
        "word": "vivent",
        "choices": [
            "يعيشون",
            "يموتون",
            "يتنفسون"
        ],
        "correctAnswer": "يعيشون"
    },
    {
        "id": 28,
        "word": "voir",
        "choices": [
            "يرى",
            "يسمع",
            "يتحدث"
        ],
        "correctAnswer": "يرى"
    },
    {
        "id": 29,
        "word": "longtemps",
        "choices": [
            "طويلاً",
            "قصيراً",
            "سريعاً"
        ],
        "correctAnswer": "طويلاً"
    },
    {
        "id": 31,
        "word": "jolie",
        "choices": [
            "جميلة",
            "قبيحة",
            "عادية"
        ],
        "correctAnswer": "جميلة"
    },
    {
        "id": 32,
        "word": "croyant",
        "choices": [
            "مؤمن",
            "كافر",
            "ضال"
        ],
        "correctAnswer": "مؤمن"
    },
    {
        "id": 33,
        "word": "après",
        "choices": [
            "بعد",
            "قبل",
            "خلال"
        ],
        "correctAnswer": "بعد"
    },
    {
        "id": 34,
        "word": "terre",
        "choices": [
            "أرض",
            "سماء",
            "بحر"
        ],
        "correctAnswer": "أرض"
    },
    {
        "id": 35,
        "word": "route",
        "choices": [
            "طريق",
            "غابة",
            "جبل"
        ],
        "correctAnswer": "طريق"
    },
    {
        "id": 36,
        "word": "déterminé",
        "choices": [
            "مصمم",
            "تردد",
            "يترك للصدفة"
        ],
        "correctAnswer": "مصمم"
    },
    {
        "id": 37,
        "word": "grogner",
        "choices": [
            "تسمير",
            "غمغمة",
            "زمزم"
        ],
        "correctAnswer": "تسمير"
    },
    {
        "id": 38,
        "word": "ignorer",
        "choices": [
            "تجاهل",
            "جهل",
            "إهمال"
        ],
        "correctAnswer": "إهمال"
    },
    {
        "id": 39,
        "word": "faire",
        "choices": [
            "أداء",
            "قام",
            "عمل"
        ],
        "correctAnswer": "أداء"
    },
    {
        "id": 40,
        "word": "commenter",
        "choices": [
            "التعليق",
            "الملاحظة",
            "الرد"
        ],
        "correctAnswer": "الملاحظة"
    }

,
        {
          "id": 41,
          "word": "lion",
          "choices": ["أسد", "نمر", "ذئب"],
          "correctAnswer": "أسد",
          "imagePath": "./lion.jpg"
        },
        {
          "id": 42,
          "word": "tigre",
          "choices": ["نمر", "أسد", "فهد"],
          "correctAnswer": "نمر",
          "imagePath": "./tigre.jpg"
        },
        {
          "id": 43,
          "word": "ours",
          "choices": ["دب", "ذئب", "فهد"],
          "correctAnswer": "دب",
          "imagePath": "./ours.jpg"
        },
        {
          "id": 44,
          "word": "cheval",
          "choices": ["حصان", "جمل", "ثور"],
          "correctAnswer": "حصان",
          "imagePath": "./cheval.jpg"
        },
        {
          "id": 45,
          "word": "dauphin",
          "choices": ["دلفين", "حوت", "سلحفاة"],
          "correctAnswer": "دلفين",
          "imagePath": "./dauphin.jpg"
        }
      
      

    ,
 
        {
          "id": 46,
          "word": "chien",
          "choices": ["كلب", "قطة", "طائر"],
          "correctAnswer": "كلب",
          "imagePath": "./chien.jpg"
        },
        {
          "id": 47,
          "word": "chat",
          "choices": ["قطة", "كلب", "فأر"],
          "correctAnswer": "قطة",
          "imagePath": "./chat.jpg"
        },
        {
          "id": 48,
          "word": "oiseau",
          "choices": ["طائر", "سمكة", "فأر"],
          "correctAnswer": "طائر",
          "imagePath": "./oiseau.jpg"
        },
        {
          "id": 49,
          "word": "poisson",
          "choices": ["سمكة", "طائر", "فأر"],
          "correctAnswer": "سمكة",
          "imagePath": "./poisson.jpg"
        },
        {
          "id": 50,
          "word": "éléphant",
          "choices": ["فيل", "حصان", "بقرة"],
          "correctAnswer": "فيل",
          "imagePath": "./elephant.jpg"
        }
   
   
      
]